hello_world/__init__.py
hello_world/test.py
nexlify_hello_world-0.1.0.dist-info/licenses/LICENCE
nexlify_hello_world-0.1.0.dist-info/METADATA
nexlify_hello_world-0.1.0.dist-info/WHEEL
nexlify_hello_world-0.1.0.dist-info/top_level.txt
nexlify_hello_world-0.1.0.dist-info/RECORD
