Metadata-Version: 2.4
Name: nexlify-hello-world
Version: 0.1.0
Summary: Un paquete simple que saluda a los usuarios.
Author: nexlify
Project-URL: Homepage, https://github.com/tu_usuario/mi_paquete
Requires-Python: >=3.6
License-File: LICENCE
Dynamic: license-file
